Metadata-Version: 2.3
Name: python-substack-tarun.1
Version: 0.1.16
Summary: A Python wrapper around the Substack API.
License: MIT
Keywords: substack
Author: Tarun Vedula
Author-email: tarun.vedula@gmail.com
Requires-Python: >=3.7,<4.0
Classifier: License :: OSI Approved :: MIT License
Classifier: Programming Language :: Python :: 3
Classifier: Programming Language :: Python :: 3.7
Classifier: Programming Language :: Python :: 3.8
Classifier: Programming Language :: Python :: 3.9
Classifier: Programming Language :: Python :: 3.10
Classifier: Programming Language :: Python :: 3.11
Classifier: Programming Language :: Python :: 3.12
Classifier: Programming Language :: Python :: 3.13
Requires-Dist: PyYAML (>=6.0,<7.0)
Requires-Dist: python-dotenv (>=0.21.0,<0.22.0)
Requires-Dist: requests (>=2.31.0,<3.0.0)
Project-URL: Homepage, https://github.com/TarunVedula/python-substack
Project-URL: Repository, https://github.com/TarunVedula/python-substack
